<?xml version="1.0" encoding="utf-8" ?>
<c2layout>
    <name>MenuOpcoes</name>
    <sid>391688791794003</sid>
    <event-sheet>eMenuOpcoes</event-sheet>
    <size>
        <width>320</width>
        <height>180</height>
    </size>
    <margins>
        <horizontal>500</horizontal>
        <vertical>500</vertical>
    </margins>
    <unbounded-scrolling>0</unbounded-scrolling>
    <layers>
        <layer name="Background" sid="874410346494084">
            <initially-visible>1</initially-visible>
            <background-color>255,255,255</background-color>
            <transparent>0</transparent>
            <parallax>
                <x>1</x>
                <y>1</y>
            </parallax>
            <zoom-rate>1</zoom-rate>
            <opacity>1</opacity>
            <force-own-texture>0</force-own-texture>
            <global>0</global>
            <use-render-cells>0</use-render-cells>
            <blend-mode>0</blend-mode>
            <effect-fallback>0</effect-fallback>
            <instances>
                <instance type="LeoBG" uid="28">
                    <properties>
                        <initial-visibility>Visible</initial-visibility>
                        <initial-animation>JumpAttack</initial-animation>
                        <initial-frame>0</initial-frame>
                        <collisions>Enabled</collisions>
                    </properties>
                    <instance-variables>
                        <estado></estado>
                        <noAr>false</noAr>
                        <sombra>0</sombra>
                        <noAr_dir></noAr_dir>
                        <atacando>false</atacando>
                        <combo>0</combo>
                        <combo_max>0</combo_max>
                        <combo_timer>0</combo_timer>
                        <acerto>0</acerto>
                        <vida>0</vida>
                        <poder>0</poder>
                    </instance-variables>
                    <blend-mode>0</blend-mode>
                    <effect-fallback>0</effect-fallback>
                    <world>
                        <x>157.129226685</x>
                        <y>85.766906738</y>
                        <z>0</z>
                        <width>45</width>
                        <height>50</height>
                        <depth>0</depth>
                        <hotspotX>0.51111114</hotspotX>
                        <hotspotY>1</hotspotY>
                        <angle>0</angle>
                        <opacity>1</opacity>
                    </world>
                </instance>
                <instance type="TylerBG" uid="29">
                    <properties>
                        <initial-visibility>Visible</initial-visibility>
                        <initial-animation>Default</initial-animation>
                        <initial-frame>0</initial-frame>
                        <collisions>Enabled</collisions>
                    </properties>
                    <blend-mode>0</blend-mode>
                    <effect-fallback>0</effect-fallback>
                    <world>
                        <x>193.820159912</x>
                        <y>105.522911072</y>
                        <z>0</z>
                        <width>60</width>
                        <height>65</height>
                        <depth>0</depth>
                        <hotspotX>0.466666669</hotspotX>
                        <hotspotY>0.492307693</hotspotY>
                        <angle>0</angle>
                        <opacity>1</opacity>
                    </world>
                </instance>
                <instance type="TrainOpacityBG" uid="30">
                    <properties>
                        <initial-visibility>Visible</initial-visibility>
                        <hotspot>Top-left</hotspot>
                    </properties>
                    <blend-mode>0</blend-mode>
                    <effect-fallback>0</effect-fallback>
                    <world>
                        <x>0</x>
                        <y>0</y>
                        <z>0</z>
                        <width>320</width>
                        <height>180</height>
                        <depth>0</depth>
                        <hotspotX>0</hotspotX>
                        <hotspotY>0</hotspotY>
                        <angle>0</angle>
                        <opacity>0.649999976</opacity>
                    </world>
                </instance>
            </instances>
            <effects />
        </layer>
        <layer name="HUD" sid="242308882700525">
            <initially-visible>1</initially-visible>
            <background-color>255,255,255</background-color>
            <transparent>1</transparent>
            <parallax>
                <x>1</x>
                <y>1</y>
            </parallax>
            <zoom-rate>1</zoom-rate>
            <opacity>1</opacity>
            <force-own-texture>0</force-own-texture>
            <global>0</global>
            <use-render-cells>0</use-render-cells>
            <blend-mode>0</blend-mode>
            <effect-fallback>0</effect-fallback>
            <instances>
                <instance type="MenuOpcoes" uid="31">
                    <properties>
                        <initial-visibility>Visible</initial-visibility>
                        <initial-animation>Default</initial-animation>
                        <initial-frame>0</initial-frame>
                        <collisions>Enabled</collisions>
                    </properties>
                    <instance-variables>
                        <estado></estado>
                    </instance-variables>
                    <blend-mode>0</blend-mode>
                    <effect-fallback>0</effect-fallback>
                    <world>
                        <x>157.678268433</x>
                        <y>89.102249146</y>
                        <z>0</z>
                        <width>150</width>
                        <height>150</height>
                        <depth>0</depth>
                        <hotspotX>0.5</hotspotX>
                        <hotspotY>0.5</hotspotY>
                        <angle>0</angle>
                        <opacity>1</opacity>
                    </world>
                </instance>
                <instance type="PlusSoundButton" uid="38">
                    <properties>
                        <initial-visibility>Visible</initial-visibility>
                        <initial-animation>Default</initial-animation>
                        <initial-frame>0</initial-frame>
                        <collisions>Enabled</collisions>
                    </properties>
                    <instance-variables>
                        <id>1</id>
                    </instance-variables>
                    <behavior-instances>
                        <behavior-instance type="Sine">
                            <properties>
                                <active-on-start>No</active-on-start>
                                <movement>Size</movement>
                                <wave>Sine</wave>
                                <period>1</period>
                                <period-random>0</period-random>
                                <period-offset>0</period-offset>
                                <period-offset-random>0</period-offset-random>
                                <magnitude>2</magnitude>
                                <magnitude-random>0</magnitude-random>
                            </properties>
                        </behavior-instance>
                    </behavior-instances>
                    <blend-mode>0</blend-mode>
                    <effect-fallback>0</effect-fallback>
                    <world>
                        <x>210</x>
                        <y>55</y>
                        <z>0</z>
                        <width>10</width>
                        <height>12</height>
                        <depth>0</depth>
                        <hotspotX>0.5</hotspotX>
                        <hotspotY>0.5</hotspotY>
                        <angle>0</angle>
                        <opacity>1</opacity>
                    </world>
                </instance>
                <instance type="MinusSoundButton" uid="40">
                    <properties>
                        <initial-visibility>Visible</initial-visibility>
                        <initial-animation>Default</initial-animation>
                        <initial-frame>0</initial-frame>
                        <collisions>Enabled</collisions>
                    </properties>
                    <instance-variables>
                        <id>1</id>
                    </instance-variables>
                    <behavior-instances>
                        <behavior-instance type="Sine">
                            <properties>
                                <active-on-start>No</active-on-start>
                                <movement>Size</movement>
                                <wave>Sine</wave>
                                <period>1</period>
                                <period-random>0</period-random>
                                <period-offset>0</period-offset>
                                <period-offset-random>0</period-offset-random>
                                <magnitude>2</magnitude>
                                <magnitude-random>0</magnitude-random>
                            </properties>
                        </behavior-instance>
                    </behavior-instances>
                    <blend-mode>0</blend-mode>
                    <effect-fallback>0</effect-fallback>
                    <world>
                        <x>150</x>
                        <y>55</y>
                        <z>0</z>
                        <width>10</width>
                        <height>5</height>
                        <depth>0</depth>
                        <hotspotX>0.5</hotspotX>
                        <hotspotY>0.5</hotspotY>
                        <angle>0</angle>
                        <opacity>1</opacity>
                    </world>
                </instance>
                <instance type="PlusSoundButton" uid="41">
                    <properties>
                        <initial-visibility>Visible</initial-visibility>
                        <initial-animation>Default</initial-animation>
                        <initial-frame>0</initial-frame>
                        <collisions>Enabled</collisions>
                    </properties>
                    <instance-variables>
                        <id>2</id>
                    </instance-variables>
                    <behavior-instances>
                        <behavior-instance type="Sine">
                            <properties>
                                <active-on-start>No</active-on-start>
                                <movement>Size</movement>
                                <wave>Sine</wave>
                                <period>1</period>
                                <period-random>0</period-random>
                                <period-offset>0</period-offset>
                                <period-offset-random>0</period-offset-random>
                                <magnitude>2</magnitude>
                                <magnitude-random>0</magnitude-random>
                            </properties>
                        </behavior-instance>
                    </behavior-instances>
                    <blend-mode>0</blend-mode>
                    <effect-fallback>0</effect-fallback>
                    <world>
                        <x>210</x>
                        <y>82.5</y>
                        <z>0</z>
                        <width>10</width>
                        <height>12</height>
                        <depth>0</depth>
                        <hotspotX>0.5</hotspotX>
                        <hotspotY>0.5</hotspotY>
                        <angle>0</angle>
                        <opacity>1</opacity>
                    </world>
                </instance>
                <instance type="MinusSoundButton" uid="43">
                    <properties>
                        <initial-visibility>Visible</initial-visibility>
                        <initial-animation>Default</initial-animation>
                        <initial-frame>0</initial-frame>
                        <collisions>Enabled</collisions>
                    </properties>
                    <instance-variables>
                        <id>2</id>
                    </instance-variables>
                    <behavior-instances>
                        <behavior-instance type="Sine">
                            <properties>
                                <active-on-start>No</active-on-start>
                                <movement>Size</movement>
                                <wave>Sine</wave>
                                <period>1</period>
                                <period-random>0</period-random>
                                <period-offset>0</period-offset>
                                <period-offset-random>0</period-offset-random>
                                <magnitude>2</magnitude>
                                <magnitude-random>0</magnitude-random>
                            </properties>
                        </behavior-instance>
                    </behavior-instances>
                    <blend-mode>0</blend-mode>
                    <effect-fallback>0</effect-fallback>
                    <world>
                        <x>150</x>
                        <y>82.5</y>
                        <z>0</z>
                        <width>10</width>
                        <height>5</height>
                        <depth>0</depth>
                        <hotspotX>0.5</hotspotX>
                        <hotspotY>0.5</hotspotY>
                        <angle>0</angle>
                        <opacity>1</opacity>
                    </world>
                </instance>
                <instance type="Cursor" uid="32">
                    <properties>
                        <initial-visibility>Invisible</initial-visibility>
                        <initial-animation>Default</initial-animation>
                        <initial-frame>0</initial-frame>
                        <collisions>Enabled</collisions>
                    </properties>
                    <instance-variables>
                        <opcaoSelecionada>1</opcaoSelecionada>
                    </instance-variables>
                    <blend-mode>0</blend-mode>
                    <effect-fallback>0</effect-fallback>
                    <world>
                        <x>109.416999817</x>
                        <y>58.080001831</y>
                        <z>0</z>
                        <width>5</width>
                        <height>5</height>
                        <depth>0</depth>
                        <hotspotX>0.5</hotspotX>
                        <hotspotY>0.5</hotspotY>
                        <angle>0</angle>
                        <opacity>1</opacity>
                    </world>
                </instance>
                <instance type="OpcaoMenu" uid="33">
                    <properties>
                        <initial-visibility>Invisible</initial-visibility>
                        <initial-animation>Default</initial-animation>
                        <initial-frame>0</initial-frame>
                        <collisions>Enabled</collisions>
                    </properties>
                    <instance-variables>
                        <opcao>1</opcao>
                        <acao>Musica</acao>
                    </instance-variables>
                    <blend-mode>0</blend-mode>
                    <effect-fallback>0</effect-fallback>
                    <world>
                        <x>168</x>
                        <y>56.031414032</y>
                        <z>0</z>
                        <width>95</width>
                        <height>20</height>
                        <depth>0</depth>
                        <hotspotX>0.5</hotspotX>
                        <hotspotY>0.5</hotspotY>
                        <angle>0</angle>
                        <opacity>1</opacity>
                    </world>
                </instance>
                <instance type="OpcaoMenu" uid="34">
                    <properties>
                        <initial-visibility>Invisible</initial-visibility>
                        <initial-animation>Default</initial-animation>
                        <initial-frame>0</initial-frame>
                        <collisions>Enabled</collisions>
                    </properties>
                    <instance-variables>
                        <opcao>2</opcao>
                        <acao>SomGeral</acao>
                    </instance-variables>
                    <blend-mode>0</blend-mode>
                    <effect-fallback>0</effect-fallback>
                    <world>
                        <x>168</x>
                        <y>82.681999207</y>
                        <z>0</z>
                        <width>95</width>
                        <height>20</height>
                        <depth>0</depth>
                        <hotspotX>0.5</hotspotX>
                        <hotspotY>0.5</hotspotY>
                        <angle>0</angle>
                        <opacity>1</opacity>
                    </world>
                </instance>
                <instance type="OpcaoMenu" uid="35">
                    <properties>
                        <initial-visibility>Invisible</initial-visibility>
                        <initial-animation>Default</initial-animation>
                        <initial-frame>0</initial-frame>
                        <collisions>Enabled</collisions>
                    </properties>
                    <instance-variables>
                        <opcao>3</opcao>
                        <acao>Voltar</acao>
                    </instance-variables>
                    <blend-mode>0</blend-mode>
                    <effect-fallback>0</effect-fallback>
                    <world>
                        <x>168</x>
                        <y>108.222999573</y>
                        <z>0</z>
                        <width>95</width>
                        <height>20</height>
                        <depth>0</depth>
                        <hotspotX>0.5</hotspotX>
                        <hotspotY>0.5</hotspotY>
                        <angle>0</angle>
                        <opacity>1</opacity>
                    </world>
                </instance>
                <instance type="MusicBarItem" uid="16">
                    <properties>
                        <initial-visibility>Visible</initial-visibility>
                        <initial-animation>Default</initial-animation>
                        <initial-frame>0</initial-frame>
                        <collisions>Enabled</collisions>
                    </properties>
                    <instance-variables>
                        <MusicBarCount>8</MusicBarCount>
                        <MusicBarId>1</MusicBarId>
                    </instance-variables>
                    <blend-mode>0</blend-mode>
                    <effect-fallback>0</effect-fallback>
                    <world>
                        <x>159</x>
                        <y>55</y>
                        <z>0</z>
                        <width>6</width>
                        <height>10</height>
                        <depth>0</depth>
                        <hotspotX>0.5</hotspotX>
                        <hotspotY>0.5</hotspotY>
                        <angle>0</angle>
                        <opacity>1</opacity>
                    </world>
                </instance>
                <instance type="MusicBarItem" uid="49">
                    <properties>
                        <initial-visibility>Visible</initial-visibility>
                        <initial-animation>Default</initial-animation>
                        <initial-frame>0</initial-frame>
                        <collisions>Enabled</collisions>
                    </properties>
                    <instance-variables>
                        <MusicBarCount>8</MusicBarCount>
                        <MusicBarId>2</MusicBarId>
                    </instance-variables>
                    <blend-mode>0</blend-mode>
                    <effect-fallback>0</effect-fallback>
                    <world>
                        <x>165</x>
                        <y>55</y>
                        <z>0</z>
                        <width>6</width>
                        <height>10</height>
                        <depth>0</depth>
                        <hotspotX>0.5</hotspotX>
                        <hotspotY>0.5</hotspotY>
                        <angle>0</angle>
                        <opacity>1</opacity>
                    </world>
                </instance>
                <instance type="MusicBarItem" uid="50">
                    <properties>
                        <initial-visibility>Visible</initial-visibility>
                        <initial-animation>Default</initial-animation>
                        <initial-frame>0</initial-frame>
                        <collisions>Enabled</collisions>
                    </properties>
                    <instance-variables>
                        <MusicBarCount>8</MusicBarCount>
                        <MusicBarId>3</MusicBarId>
                    </instance-variables>
                    <blend-mode>0</blend-mode>
                    <effect-fallback>0</effect-fallback>
                    <world>
                        <x>171</x>
                        <y>55</y>
                        <z>0</z>
                        <width>6</width>
                        <height>10</height>
                        <depth>0</depth>
                        <hotspotX>0.5</hotspotX>
                        <hotspotY>0.5</hotspotY>
                        <angle>0</angle>
                        <opacity>1</opacity>
                    </world>
                </instance>
                <instance type="MusicBarItem" uid="51">
                    <properties>
                        <initial-visibility>Visible</initial-visibility>
                        <initial-animation>Default</initial-animation>
                        <initial-frame>0</initial-frame>
                        <collisions>Enabled</collisions>
                    </properties>
                    <instance-variables>
                        <MusicBarCount>8</MusicBarCount>
                        <MusicBarId>4</MusicBarId>
                    </instance-variables>
                    <blend-mode>0</blend-mode>
                    <effect-fallback>0</effect-fallback>
                    <world>
                        <x>177</x>
                        <y>55</y>
                        <z>0</z>
                        <width>6</width>
                        <height>10</height>
                        <depth>0</depth>
                        <hotspotX>0.5</hotspotX>
                        <hotspotY>0.5</hotspotY>
                        <angle>0</angle>
                        <opacity>1</opacity>
                    </world>
                </instance>
                <instance type="MusicBarItem" uid="52">
                    <properties>
                        <initial-visibility>Visible</initial-visibility>
                        <initial-animation>Default</initial-animation>
                        <initial-frame>0</initial-frame>
                        <collisions>Enabled</collisions>
                    </properties>
                    <instance-variables>
                        <MusicBarCount>8</MusicBarCount>
                        <MusicBarId>5</MusicBarId>
                    </instance-variables>
                    <blend-mode>0</blend-mode>
                    <effect-fallback>0</effect-fallback>
                    <world>
                        <x>183</x>
                        <y>55</y>
                        <z>0</z>
                        <width>6</width>
                        <height>10</height>
                        <depth>0</depth>
                        <hotspotX>0.5</hotspotX>
                        <hotspotY>0.5</hotspotY>
                        <angle>0</angle>
                        <opacity>1</opacity>
                    </world>
                </instance>
                <instance type="MusicBarItem" uid="53">
                    <properties>
                        <initial-visibility>Visible</initial-visibility>
                        <initial-animation>Default</initial-animation>
                        <initial-frame>0</initial-frame>
                        <collisions>Enabled</collisions>
                    </properties>
                    <instance-variables>
                        <MusicBarCount>8</MusicBarCount>
                        <MusicBarId>6</MusicBarId>
                    </instance-variables>
                    <blend-mode>0</blend-mode>
                    <effect-fallback>0</effect-fallback>
                    <world>
                        <x>189</x>
                        <y>55</y>
                        <z>0</z>
                        <width>6</width>
                        <height>10</height>
                        <depth>0</depth>
                        <hotspotX>0.5</hotspotX>
                        <hotspotY>0.5</hotspotY>
                        <angle>0</angle>
                        <opacity>1</opacity>
                    </world>
                </instance>
                <instance type="MusicBarItem" uid="54">
                    <properties>
                        <initial-visibility>Visible</initial-visibility>
                        <initial-animation>Default</initial-animation>
                        <initial-frame>0</initial-frame>
                        <collisions>Enabled</collisions>
                    </properties>
                    <instance-variables>
                        <MusicBarCount>8</MusicBarCount>
                        <MusicBarId>7</MusicBarId>
                    </instance-variables>
                    <blend-mode>0</blend-mode>
                    <effect-fallback>0</effect-fallback>
                    <world>
                        <x>195</x>
                        <y>55</y>
                        <z>0</z>
                        <width>6</width>
                        <height>10</height>
                        <depth>0</depth>
                        <hotspotX>0.5</hotspotX>
                        <hotspotY>0.5</hotspotY>
                        <angle>0</angle>
                        <opacity>1</opacity>
                    </world>
                </instance>
                <instance type="MusicBarItem" uid="55">
                    <properties>
                        <initial-visibility>Visible</initial-visibility>
                        <initial-animation>Default</initial-animation>
                        <initial-frame>0</initial-frame>
                        <collisions>Enabled</collisions>
                    </properties>
                    <instance-variables>
                        <MusicBarCount>8</MusicBarCount>
                        <MusicBarId>8</MusicBarId>
                    </instance-variables>
                    <blend-mode>0</blend-mode>
                    <effect-fallback>0</effect-fallback>
                    <world>
                        <x>201</x>
                        <y>55</y>
                        <z>0</z>
                        <width>6</width>
                        <height>10</height>
                        <depth>0</depth>
                        <hotspotX>0.5</hotspotX>
                        <hotspotY>0.5</hotspotY>
                        <angle>0</angle>
                        <opacity>1</opacity>
                    </world>
                </instance>
                <instance type="SoundBarItem" uid="39">
                    <properties>
                        <initial-visibility>Visible</initial-visibility>
                        <initial-animation>Default</initial-animation>
                        <initial-frame>0</initial-frame>
                        <collisions>Enabled</collisions>
                    </properties>
                    <instance-variables>
                        <SoundBarId>1</SoundBarId>
                        <SoundBarCount>8</SoundBarCount>
                    </instance-variables>
                    <blend-mode>0</blend-mode>
                    <effect-fallback>0</effect-fallback>
                    <world>
                        <x>159</x>
                        <y>82.5</y>
                        <z>0</z>
                        <width>6</width>
                        <height>10</height>
                        <depth>0</depth>
                        <hotspotX>0.5</hotspotX>
                        <hotspotY>0.5</hotspotY>
                        <angle>0</angle>
                        <opacity>1</opacity>
                    </world>
                </instance>
                <instance type="SoundBarItem" uid="42">
                    <properties>
                        <initial-visibility>Visible</initial-visibility>
                        <initial-animation>Default</initial-animation>
                        <initial-frame>0</initial-frame>
                        <collisions>Enabled</collisions>
                    </properties>
                    <instance-variables>
                        <SoundBarId>2</SoundBarId>
                        <SoundBarCount>8</SoundBarCount>
                    </instance-variables>
                    <blend-mode>0</blend-mode>
                    <effect-fallback>0</effect-fallback>
                    <world>
                        <x>165</x>
                        <y>82.5</y>
                        <z>0</z>
                        <width>6</width>
                        <height>10</height>
                        <depth>0</depth>
                        <hotspotX>0.5</hotspotX>
                        <hotspotY>0.5</hotspotY>
                        <angle>0</angle>
                        <opacity>1</opacity>
                    </world>
                </instance>
                <instance type="SoundBarItem" uid="56">
                    <properties>
                        <initial-visibility>Visible</initial-visibility>
                        <initial-animation>Default</initial-animation>
                        <initial-frame>0</initial-frame>
                        <collisions>Enabled</collisions>
                    </properties>
                    <instance-variables>
                        <SoundBarId>3</SoundBarId>
                        <SoundBarCount>8</SoundBarCount>
                    </instance-variables>
                    <blend-mode>0</blend-mode>
                    <effect-fallback>0</effect-fallback>
                    <world>
                        <x>171</x>
                        <y>82.5</y>
                        <z>0</z>
                        <width>6</width>
                        <height>10</height>
                        <depth>0</depth>
                        <hotspotX>0.5</hotspotX>
                        <hotspotY>0.5</hotspotY>
                        <angle>0</angle>
                        <opacity>1</opacity>
                    </world>
                </instance>
                <instance type="SoundBarItem" uid="57">
                    <properties>
                        <initial-visibility>Visible</initial-visibility>
                        <initial-animation>Default</initial-animation>
                        <initial-frame>0</initial-frame>
                        <collisions>Enabled</collisions>
                    </properties>
                    <instance-variables>
                        <SoundBarId>4</SoundBarId>
                        <SoundBarCount>8</SoundBarCount>
                    </instance-variables>
                    <blend-mode>0</blend-mode>
                    <effect-fallback>0</effect-fallback>
                    <world>
                        <x>177</x>
                        <y>82.5</y>
                        <z>0</z>
                        <width>6</width>
                        <height>10</height>
                        <depth>0</depth>
                        <hotspotX>0.5</hotspotX>
                        <hotspotY>0.5</hotspotY>
                        <angle>0</angle>
                        <opacity>1</opacity>
                    </world>
                </instance>
                <instance type="SoundBarItem" uid="58">
                    <properties>
                        <initial-visibility>Visible</initial-visibility>
                        <initial-animation>Default</initial-animation>
                        <initial-frame>0</initial-frame>
                        <collisions>Enabled</collisions>
                    </properties>
                    <instance-variables>
                        <SoundBarId>5</SoundBarId>
                        <SoundBarCount>8</SoundBarCount>
                    </instance-variables>
                    <blend-mode>0</blend-mode>
                    <effect-fallback>0</effect-fallback>
                    <world>
                        <x>183</x>
                        <y>82.5</y>
                        <z>0</z>
                        <width>6</width>
                        <height>10</height>
                        <depth>0</depth>
                        <hotspotX>0.5</hotspotX>
                        <hotspotY>0.5</hotspotY>
                        <angle>0</angle>
                        <opacity>1</opacity>
                    </world>
                </instance>
                <instance type="SoundBarItem" uid="59">
                    <properties>
                        <initial-visibility>Visible</initial-visibility>
                        <initial-animation>Default</initial-animation>
                        <initial-frame>0</initial-frame>
                        <collisions>Enabled</collisions>
                    </properties>
                    <instance-variables>
                        <SoundBarId>6</SoundBarId>
                        <SoundBarCount>8</SoundBarCount>
                    </instance-variables>
                    <blend-mode>0</blend-mode>
                    <effect-fallback>0</effect-fallback>
                    <world>
                        <x>189</x>
                        <y>82.5</y>
                        <z>0</z>
                        <width>6</width>
                        <height>10</height>
                        <depth>0</depth>
                        <hotspotX>0.5</hotspotX>
                        <hotspotY>0.5</hotspotY>
                        <angle>0</angle>
                        <opacity>1</opacity>
                    </world>
                </instance>
                <instance type="SoundBarItem" uid="60">
                    <properties>
                        <initial-visibility>Visible</initial-visibility>
                        <initial-animation>Default</initial-animation>
                        <initial-frame>0</initial-frame>
                        <collisions>Enabled</collisions>
                    </properties>
                    <instance-variables>
                        <SoundBarId>7</SoundBarId>
                        <SoundBarCount>8</SoundBarCount>
                    </instance-variables>
                    <blend-mode>0</blend-mode>
                    <effect-fallback>0</effect-fallback>
                    <world>
                        <x>195</x>
                        <y>82.5</y>
                        <z>0</z>
                        <width>6</width>
                        <height>10</height>
                        <depth>0</depth>
                        <hotspotX>0.5</hotspotX>
                        <hotspotY>0.5</hotspotY>
                        <angle>0</angle>
                        <opacity>1</opacity>
                    </world>
                </instance>
                <instance type="SoundBarItem" uid="61">
                    <properties>
                        <initial-visibility>Visible</initial-visibility>
                        <initial-animation>Default</initial-animation>
                        <initial-frame>0</initial-frame>
                        <collisions>Enabled</collisions>
                    </properties>
                    <instance-variables>
                        <SoundBarId>8</SoundBarId>
                        <SoundBarCount>8</SoundBarCount>
                    </instance-variables>
                    <blend-mode>0</blend-mode>
                    <effect-fallback>0</effect-fallback>
                    <world>
                        <x>201</x>
                        <y>82.5</y>
                        <z>0</z>
                        <width>6</width>
                        <height>10</height>
                        <depth>0</depth>
                        <hotspotX>0.5</hotspotX>
                        <hotspotY>0.5</hotspotY>
                        <angle>0</angle>
                        <opacity>1</opacity>
                    </world>
                </instance>
            </instances>
            <effects />
        </layer>
    </layers>
    <nonworld-instances />
    <effects />
</c2layout>
